setup.py
tranx/__init__.py
tranx.egg-info/PKG-INFO
tranx.egg-info/SOURCES.txt
tranx.egg-info/dependency_links.txt
tranx.egg-info/entry_points.txt
tranx.egg-info/not-zip-safe
tranx.egg-info/requires.txt
tranx.egg-info/top_level.txt