Metadata-Version: 2.1
Name: tranx
Version: 0.0.2
Summary: Translating XLIFF tool
Home-page: https://github.com/dicaso/tranx
Author: Christophe Van Neste
Author-email: beukueb@gmail.com
License: GNU GENERAL PUBLIC LICENSE
Platform: UNKNOWN
Provides-Extra: google
